test_poooooooooooooooooc/__init__.py
test_poooooooooooooooooc-0.0.1.dist-info/METADATA
test_poooooooooooooooooc-0.0.1.dist-info/WHEEL
test_poooooooooooooooooc-0.0.1.dist-info/top_level.txt
test_poooooooooooooooooc-0.0.1.dist-info/RECORD
