Metadata-Version: 2.4
Name: test-poooooooooooooooooc
Version: 0.0.1
Summary: Temporary test package for verification
Requires-Python: >=3.7
